news_fetcher/db.py
news_fetcher/models.py
news_fetcher/module.py
news_fetcher/news_fetcher.py
news_fetcher/prostoprosport.py
news_fetcher/rss.py
news_fetcher/test.py
news_fetcher/utils.py
news_fetcher/wikitext.py
news_fetcher-0.3.1.dist-info/LICENSE
news_fetcher-0.3.1.dist-info/METADATA
news_fetcher-0.3.1.dist-info/WHEEL
news_fetcher-0.3.1.dist-info/RECORD
