Metadata-Version: 2.1
Name: news_fetcher
Version: 0.3.1
Summary: Script to fetch news using API and convert to wiki-text
Home-page: https://github.com/ArtUshak/prostoprosport_news_fetcher/
License: MIT
Author: Artiom Khandamirov
Author-email: t9max@yandex.ru
Requires-Python: >=3.8.1,<4.0.0
Classifier: Development Status :: 4 - Beta
Classifier: Environment :: Console
Classifier: Framework :: aiohttp
Classifier: License :: OSI Approved :: MIT License
Classifier: Programming Language :: Python :: 3
Classifier: Programming Language :: Python :: 3.9
Classifier: Programming Language :: Python :: 3.10
Classifier: Programming Language :: Python :: 3.11
Classifier: Programming Language :: Python :: 3.12
Requires-Dist: aiohttp (>=3.8.1,<4.0.0)
Requires-Dist: beautifulsoup4 (>=4.11.1,<5.0.0)
Requires-Dist: click (>=8.1.3,<9.0.0)
Requires-Dist: feedparser (>=6.0.10,<7.0.0)
Requires-Dist: tortoise-orm[accel,asyncpg] (>=0.19.1,<0.20.0)
Project-URL: Repository, https://github.com/ArtUshak/prostoprosport_news_fetcher/
